Workbook
Name category: Sheet1!$C$2:$C$15346
Name city: Sheet1!$L$2:$L$15346
Name customer_type: Sheet1!$I$2:$I$15346
Name delivery_date: Sheet1!$H$2:$H$15346
Name discount: Sheet1!$E$2:$E$15346
Name Discount_Value: Sheet1!#REF!
Name Net_Revenue: Sheet1!#REF!
Name order_date: Sheet1!$G$2:$G$15346
Name order_id: Sheet1!$A$2:$A$15346
Name payment_mode: Sheet1!$J$2:$J$15346
Name profit: Sheet1!$K$2:$K$15346
Name quantity: Sheet1!$F$2:$F$15346
Name region: Sheet1!$B$2:$B$15346
Name sales: Sheet1!$D$2:$D$15346

Sheet Sheet1
A1: order_id | B1: region | C1: category | D1: sales | E1: discount | F1: quantity | G1: order_date | H1: delivery_date | I1: customer_type | J1: payment_mode | K1: profit | L1: city
A2: ORD100000 | B2: East | C2: Clothing | D2: 713.49 | E2: 0.31 | F2: 3 | G2: 45015 | H2: 45017 | I2: Member | J2: UPI | K2: 114.72 | L2: Pune
A3: ORD100001 | B3: West | C3: Electronics | D3: 3802.97 | E3: 0.38 | F3: 4 | G3: 45166 | H3: 45172 | I3: Regular | J3: Card | K3: 971.41 | L3: Hyderabad | S3: 35.9946
A4: ORD100002 | B4: North | C4: Home Care | D4: 3588.97 | E4: 0.1 | F4: 7 | G4: 45360 | H4: 45366 | I4: Regular | J4: Cash | K4: 769.08 | L4: Bangalore
A5: ORD100003 | B5: East | C5: Electronics | D5: 1160.86 | E5: 0.27 | F5: 5 | G5: 45578 | H5: 45584 | I5: Member | J5: UPI | K5: 71.61 | L5: Pune
A6: ORD100004 | B6: East | C6: Electronics | D6: 3071.32 | E6: 0 | F6: 7 | G6: 45022 | H6: 45025 | I6: New | J6: Cash | K6: 621.92 | L6: Bangalore | M6: total sale | O6: =SUM(sales) -> 39262878
A7: ORD100005 | B7: West | C7: Grocery | D7: 2566.18 | E7: 0.02 | F7: 6 | G7: 45108 | H7: 45111 | I7: Member | J7: UPI | K7: 578.94 | L7: Mumbai | M7: total profit | O7: =SUM(O6*10%) -> 3926287.8
A8: ORD100006 | B8: North | C8: Personal Care | D8: 398 | E8: 0.16 | F8: 4 | G8: 45119 | H8: 45124 | I8: New | J8: Cash | K8: 110.31 | L8: Mumbai | M8: marketing budget | N8: 10% of total profit | S8: =ROUND(S3,) -> 36
A9: ORD100007 | B9: North | C9: Personal Care | D9: 1462.95 | E9: 0.23 | F9: 2 | G9: 45064 | H9: 45066 | I9: Regular | J9: UPI | K9: 91.68 | L9: Bangalore | O9: =O6*0.1 -> 3926287.8
A10: ORD100008 | B10: East | C10: Personal Care | D10: 4997.47 | E10: 0.29 | F10: 6 | G10: 45296 | H10: 45299 | I10: Regular | J10: Card | K10: 995.78 | L10: Delhi | M10: rahul@gmail.com
A11: ORD100009 | B11: South | C11: Grocery | D11: 587.72 | E11: 0.44 | F11: 6 | G11: 45514 | H11: 45521 | I11: New | J11: Cash | K11: 102.96 | L11: Pune
A12: ORD100010 | B12: East | C12: Clothing | D12: 2581.42 | E12: 0.39 | F12: 6 | G12: 45419 | H12: 45420 | I12: Regular | J12: Cash | K12: 542.82 | L12: Bangalore | Q12: 29604
A13: ORD100011 | B13: East | C13: Clothing | D13: 4261.74 | E13: 0.15 | F13: 1 | G13: 45171 | H13: 45172 | I13: New | J13: UPI | K13: 1028.47 | L13: Pune | Q13: 0.72
A14: ORD100012 | B14: East | C14: Home Care | D14: 1573.19 | E14: 0.37 | F14: 6 | G14: 45331 | H14: 45338 | I14: New | J14: Cash | K14: 131.5 | L14: Bangalore | O14: =WEEKDAY(O22) -> 2
A15: ORD100013 | B15: East | C15: Clothing | D15: 1377.47 | E15: 0.27 | F15: 2 | G15: 45074 | H15: 45075 | I15: Member | J15: Cash | K15: 255.49 | L15: Delhi
A16: ORD100014 | B16: West | C16: Clothing | D16: 4464.89 | E16: 0.39 | F16: 5 | G16: 45296 | H16: 45303 | I16: Regular | J16: UPI | K16: 804.36 | L16: Pune | O16: =ABS(Q18) -> 10.06534
A17: ORD100015 | B17: North | C17: Personal Care | D17: 1593.67 | E17: 0.21 | F17: 7 | G17: 45583 | H17: 45587 | I17: Member | J17: Card | K17: 284.91 | L17: Chennai | O17: =ABS(-10) -> 10 | Q17: 95.6
A18: ORD100016 | B18: West | C18: Electronics | D18: 3292.32 | E18: 0.05 | F18: 1 | G18: 45042 | H18: 45043 | I18: Member | J18: Card | K18: 504.83 | L18: Mumbai | Q18: 10.06534
A19: ORD100017 | B19: West | C19: Clothing | D19: 3727.53 | E19: 0.31 | F19: 5 | G19: 45228 | H19: 45235 | I19: Regular | J19: Card | K19: 978.07 | L19: Chennai | O19: =YEAR(G3) -> 2023
A20: ORD100018 | B20: West | C20: Clothing | D20: 3964.23 | E20: 0.28 | F20: 9 | G20: 45448 | H20: 45451 | I20: Member | J20: UPI | K20: 260.95 | L20: Bangalore
A21: ORD100019 | B21: East | C21: Grocery | D21: 4974.32 | E21: 0.48 | F21: 3 | G21: 45047 | H21: 45051 | I21: Regular | J21: Card | K21: 727.29 | L21: Delhi | Q21: 46237
A22: ORD100020 | B22: South | C22: Home Care | D22: 4035.64 | E22: 0.08 | F22: 2 | G22: 45586 | H22: 45593 | I22: Regular | J22: Cash | K22: 798.81 | L22: Delhi | N22: today | O22: =TODAY() -> 46237
A23: ORD100021 | B23: North | C23: Grocery | D23: 3319.36 | E23: 0.33 | F23: 2 | G23: 45153 | H23: 45159 | I23: Member | J23: Cash | K23: 920.22 | L23: Bangalore | N23: now | O23: =NOW() -> 46237.787
A24: ORD100022 | B24: South | C24: Personal Care | D24: 4487.77 | E24: 0.24 | F24: 3 | G24: 45657 | H24: 45659 | I24: Regular | J24: Card | K24: 931.37 | L24: Pune | N24: month | O24: =MONTH(O22) -> 8
A25: ORD100023 | B25: West | C25: Electronics | D25: 4538.15 | E25: 0.19 | F25: 1 | G25: 45005 | H25: 45008 | I25: Regular | J25: Cash | K25: 375.7 | L25: Delhi
A26: ORD100024 | B26: West | C26: Home Care | D26: 4868.52 | E26: 0.4 | F26: 2 | G26: 45272 | H26: 45273 | I26: Regular | J26: Cash | K26: 1072.26 | L26: Mumbai
A27: ORD100025 | B27: South | C27: Grocery | D27: 3904.68 | E27: 0.41 | F27: 6 | G27: 45066 | H27: 45072 | I27: Regular | J27: Card | K27: 526.66 | L27: Hyderabad
A28: ORD100026 | B28: South | C28: Clothing | D28: 1055.14 | E28: 0.36 | F28: 8 | G28: 45462 | H28: 45468 | I28: Member | J28: UPI | K28: 207.61 | L28: Chennai
A29: ORD100027 | B29: South | C29: Clothing | D29: 3578.05 | E29: 0.04 | F29: 4 | G29: 45215 | H29: 45217 | I29: New | J29: Card | K29: 689.74 | L29: Mumbai
A30: ORD100028 | B30: West | C30: Home Care | D30: 468.13 | E30: 0.17 | F30: 2 | G30: 45255 | H30: 45261 | I30: Member | J30: UPI | K30: 43.58 | L30: Hyderabad
A31: ORD100029 | B31: West | C31: Clothing | D31: 1658.02 | E31: 0.02 | F31: 5 | G31: 45356 | H31: 45357 | I31: New | J31: Cash | K31: 422.33 | L31: Delhi
A32: ORD100030 | B32: North | C32: Grocery | D32: 667.46 | E32: 0.17 | F32: 3 | G32: 45026 | H32: 45031 | I32: New | J32: Card | K32: 123.49 | L32: Pune
A33: ORD100031 | B33: North | C33: Grocery | D33: 4754.72 | E33: 0.32 | F33: 5 | G33: 45527 | H33: 45531 | I33: New | J33: Cash | K33: 697.03 | L33: Chennai
A34: ORD100032 | B34: West | C34: Clothing | D34: 1759.9 | E34: 0.26 | F34: 3 | G34: 44933 | H34: 44939 | I34: Regular | J34: Cash | K34: 178.58 | L34: Delhi
A35: ORD100033 | B35: South | C35: Clothing | D35: 3594.76 | E35: 0.35 | F35: 4 | G35: 45097 | H35: 45099 | I35: New | J35: UPI | K35: 1002.97 | L35: Delhi
A36: ORD100034 | B36: South | C36: Personal Care | D36: 2899.46 | E36: 0.28 | F36: 5 | G36: 45189 | H36: 45190 | I36: Regular | J36: Cash | K36: 320.43 | L36: Bangalore
... A15346: ORD115344 | B15346: South | C15346: Grocery | D15346: 4984.32 | E15346: 0.21 | F15346: 3 | G15346: 45248 | H15346: 45249 | I15346: New | J15346: Card | K15346: 909.1 | L15346: Bangalore

Sheet Sheet8
A1: 10
A2: 20
A3: 30
A4: 40
D8: =SUM(Sheet8!A1:A4) -> 100
C9: sum | D9: =SUM(A1:A4) -> 100
C10: min | D10: =MIN(A1:A4) -> 10
C11: max | D11: =MAX(A1:A4) -> 40
C12: count | D12: =COUNT(A1:A4) -> 4
C13: avg | D13: =AVERAGE(A1:A4) -> 25

Sheet Sheet6
B1: 1 | C1: 2 | D1: 3 | E1: 4
A2: 1
A3: 2
A4: 3
A5: 4

Sheet Sheet7

Sheet Sheet4
A1: Fruit | B1: Price | C1: City | I1: email | K1: .in
A2: Apple | B2: 50 | C2: Mumbai | H2: xyz | I2: xyz@domain.com | K2: =SUBSTITUTE(I2,".com",".in") -> xyz@domain.in | L2: 111222333 | M2: =REPLACE(L2,4,3,"***") -> 111***333
A3: Banana | B3: 100 | C3: Vashi | D3: Total Sum Of Apple | E3: Count Of Apple | F3: Average Price Of Apple | H3: abc | I3: abc@domain.com | K3: =SUBSTITUTE(I3,".com",".in") -> abc@domain.in | L3: 222333444 | M3: =REPLACE(L3,4,3,"***") -> 222***444
A4: Orange | B4: 150 | C4: Thane | D4: =SUMIF(A2:A13,"Apple",B2:B13) -> 2000 | E4: =COUNTIF(A2:A13,"Apple") -> 6 | H4: pqr | I4: pqr@domain.com | K4: =SUBSTITUTE(I4,".com",".in") -> pqr@domain.in
A5: Apple | B5: 200 | C5: Panvel | D5: Mumbai Avg | H5: mno | I5: mno@domain.com | K5: =SUBSTITUTE(I5,".com",".in") -> mno@domain.in
A6: kiwi | B6: 250 | C6: Mumbai | D6: =AVERAGEIFS(B2:B13,A2:A13,"Apple",C2:C13,"Mumbai") -> 383.33333 | H6: lst | I6: lst@domain.com | K6: =SUBSTITUTE(I6,".com",".in") -> lst@domain.in
A7: Apple | B7: 300 | C7: Vashi | H7: uvx | I7: uvx@domain.com | K7: =SUBSTITUTE(I7,".com",".in") -> uvx@domain.in
A8: Apple | B8: 350 | C8: Thane | H8: xyz | I8: xyz@domain.com | K8: =SUBSTITUTE(I8,".com",".in") -> xyz@domain.in
A9: Banana | B9: 400 | C9: Panvel | H9: abc | I9: abc@domain.com | K9: =SUBSTITUTE(I9,".com",".in") -> abc@domain.in
A10: Orange | B10: 450 | C10: Mumbai | H10: pqr | I10: pqr@domain.com | K10: =SUBSTITUTE(I10,".com",".in") -> pqr@domain.in
A11: Apple | B11: 500 | C11: Mumbai | H11: mno | I11: mno@domain.com | K11: =SUBSTITUTE(I11,".com",".in") -> mno@domain.in
A12: kiwi | B12: 550 | C12: Thane | H12: lst | I12: lst@domain.com | K12: =SUBSTITUTE(I12,".com",".in") -> lst@domain.in
A13: Apple | B13: 600 | C13: Mumbai | H13: uvx | I13: uvx@domain.com | K13: =SUBSTITUTE(I13,".com",".in") -> uvx@domain.in

Sheet Sheet2
A1: Roll no | B1: Name | C1: Marks
A2: 1 | B2: Rahul | C2: =VLOOKUP(A2,Sheet3!$A$1:$C$9,MATCH("Marks",Sheet3!$1:$1,0),FALSE) -> 65
A3: 2 | B3: Kunal | C3: =VLOOKUP(A3,Sheet3!$A$1:$C$9,MATCH("Marks",Sheet3!$1:$1,0),FALSE) -> 76
A4: 6 | B4: Hardik | C4: =VLOOKUP(A4,Sheet3!$A$1:$C$9,MATCH("Marks",Sheet3!$1:$1,0),FALSE) -> 77
A5: 4 | B5: Dhoni | C5: =VLOOKUP(A5,Sheet3!$A$1:$C$9,MATCH("Marks",Sheet3!$1:$1,0),FALSE) -> 34
A6: 5 | B6: Rohan | C6: =VLOOKUP(A6,Sheet3!$A$1:$C$9,MATCH("Marks",Sheet3!$1:$1,0),FALSE) -> 90
A7: 3 | B7: Kurnal | C7: =VLOOKUP(A7,Sheet3!$A$1:$C$9,MATCH("Marks",Sheet3!$1:$1,0),FALSE) -> 89
A8: 7 | B8: Pandya | C8: =VLOOKUP(A8,Sheet3!$A$1:$C$9,MATCH("Marks",Sheet3!$1:$1,0),FALSE) -> 56
A9: 8 | B9: Mahendra | C9: =VLOOKUP(A9,Sheet3!$A$1:$C$9,MATCH("Marks",Sheet3!$1:$1,0),FALSE) -> 87

Sheet Sheet5
A1: Rollno | B1: 1 | C1: 2 | D1: 3 | E1: 4 | F1: 5 | G1: 6 | H1: 7 | I1: 8 | J1: 9
A2: Name | B2: Rahul | C2: Kunal | D2: Hardik | E2: Dhoni | F2: Rahul | G2: Kunal | H2: Hardik | I2: Dhoni | J2: Rahul
A3: Marks | B3: 34 | C3: 45 | D3: 67 | E3: 89 | F3: 98 | G3: 87 | H3: 76 | I3: 65 | J3: 54
G10: =HLOOKUP(7,B1:J3,3,FALSE) -> 76

Sheet Sheet3
A1: Roll no | C1: Marks
A2: 1 | C2: 65
A3: 2 | C3: 76
A4: 3 | C4: 89
A5: 4 | C5: 34
A6: 5 | C6: 90
A7: 6 | C7: 77
A8: 7 | C8: 56
A9: 8 | C9: 87
E10: =MATCH("Marks",1:1,0) -> 3
